<?xml version="1.0" encoding="utf-8"?>
<List xmlns:ows="Microsoft SharePoint" Title="SecurityEscortRouteTemplate" FolderCreation="FALSE" Direction="$Resources:Direction;" Url="Lists/ShepherdWebsite-SecurityEscortRouteTemplate" BaseType="0" xmlns="http://schemas.microsoft.com/sharepoint/">
  <MetaData>
    <ContentTypes>
      <ContentType ID="0x01004d883ad19a284d1f826ea7b4e70f0aca"
                   Name="SecurityEscortCatalog"
                   Group="CAS Smart Factory Shepherd"
                   Description="$Resources:CASSmartFactoryShepherd,CAS_SecurityEscortCatalogListCT"
                   Inherits="TRUE"
                   Overwrite="FALSE">
        <Folder TargetName="_cts/SecurityEscortCatalog" />
        <FieldRefs>
          <FieldRef ID="{fa564e0f-0c70-4ab9-b863-0177e6ddd247}" Name="Title" DisplayName="$Resources:CASSmartFactoryShepherd,CAS_SecurityEscortRoute" />
          <FieldRef ID="{40070CB4-6ED0-4024-9269-70DAC8932C42}" Name="SecurityEscortCatalog2BusinessDescriptionTitle" />
          <FieldRef ID="{4E19EC40-3A94-453E-ABEA-4DCBE1BF8ECD}" Name="EscortDestination" />
          <FieldRef ID="{40088770-43E3-441B-9973-D3B093DC131C}" Name="RemarkMM" />
          <FieldRef ID="{B5D7D15B-E7BA-4768-B746-AC71D70EF53F}" Name="FreightPayerTitle" />
          <FieldRef ID="{7BE8C54A-009F-436D-80C3-2E13A3F4A514}" Name="MaterialMaster" />
          <FieldRef ID="{C7CA4AA6-8399-4714-A4A4-42145FABA936}" Name="PartnerTitle" />
          <FieldRef ID="{D73A3F7D-6892-4A46-90EE-39BEB668944A}" Name="SecurityCost" />
          <FieldRef ID="{E1C985AA-F1A4-4275-87D3-EE0DF7B44223}" Name="CurrencyTitle" />
          <FieldRef ID="{DBCFB052-FB4A-46C1-B72E-BB92F9825142}" Name="SecurityEscrotPO" />
        </FieldRefs>
        <XmlDocuments>
          <XmlDocument NamespaceURI="http://schemas.microsoft.com/sharepoint/v3/contenttype/forms">
            <FormTemplates xmlns="http://schemas.microsoft.com/sharepoint/v3/contenttype/forms">
              <Display>ListForm</Display>
              <Edit>ListForm</Edit>
              <New>ListForm</New>
            </FormTemplates>
          </XmlDocument>
        </XmlDocuments>
      </ContentType>
    </ContentTypes>
    <Fields>
      <Field Name="EscortDestination" ID="{4e19ec40-3a94-453e-abea-4dcbe1bf8ecd}" Type="Text" DisplayName="Escort Destination" Group="CAS Smart Factory Shepherd" />
      <Field Name="SecurityEscrotPO" ID="{dbcfb052-fb4a-46c1-b72e-bb92f9825142}" Type="Text" DisplayName="Security Escort PO" Group="CAS Smart Factory Shepherd" />
      <Field DisplayName="Material Master" Name="MaterialMaster" Type="Text" ID="{7be8c54a-009f-436d-80c3-2e13a3f4a514}" Group="CAS Smart Factory Shepherd" />
      <Field DisplayName="Security Cost" Name="SecurityCost" Type="Number" ID="{d73a3f7d-6892-4a46-90ee-39beb668944a}" Group="CAS Smart Factory Shepherd" Description="Security Cost" />
      <Field DisplayName="Remark MM" Name="RemarkMM" Type="Text" ID="{40088770-43e3-441b-9973-d3b093dc131c}" Group="CAS Smart Factory Shepherd" />
      <Field Name="SecurityEscortCatalog2BusinessDescriptionTitle" ID="{40070cb4-6ed0-4024-9269-70dac8932c42}" Type="Lookup" List="Lists/BusinessDescriptionList" ShowField="Title" UnlimitedLengthInDocumentLibrary="False" Indexed="True" RelationshipDeleteBehavior="None" DisplayName="Business Description" Group="CAS Smart Factory Shepherd" Required="True" Hidden="False" DisplaceOnUpgrade="True" EnforceUniqueValues="False" ReadOnly="False" />
      <Field Name="FreightPayerTitle" ID="{b5d7d15b-e7ba-4768-b746-ac71d70ef53f}" Type="Lookup" List="Lists/FreightPayerList" ShowField="Title" UnlimitedLengthInDocumentLibrary="False" Indexed="True" RelationshipDeleteBehavior="None" DisplayName="Freight Payer" Group="CAS Smart Factory Shepherd" Required="False" Hidden="False" DisplaceOnUpgrade="True" EnforceUniqueValues="False" ReadOnly="False" />
      <Field Name="CurrencyTitle" ID="{e1c985aa-f1a4-4275-87d3-ee0df7b44223}" Type="Lookup" List="Lists/CurrencyList" ShowField="Title" UnlimitedLengthInDocumentLibrary="False" Indexed="True" RelationshipDeleteBehavior="None" DisplayName="Currency" Group="CAS Smart Factory Shepherd" Required="False" Hidden="False" DisplaceOnUpgrade="True" EnforceUniqueValues="False" ReadOnly="False" />
      <Field Name="PartnerTitle" ID="{c7ca4aa6-8399-4714-a4a4-42145faba936}" Type="Lookup" List="Lists/JTIPartnerList" ShowField="Title" UnlimitedLengthInDocumentLibrary="False" Indexed="True" RelationshipDeleteBehavior="None" DisplayName="Vendor Name" Group="CAS Smart Factory Shepherd" Required="False" Hidden="False" DisplaceOnUpgrade="True" EnforceUniqueValues="False" ReadOnly="False" />
    </Fields>
    <Views>
      <View BaseViewID="0" Type="HTML" MobileView="TRUE" TabularView="FALSE">
        <Toolbar Type="Standard" />
        <XslLink Default="TRUE">main.xsl</XslLink>
        <RowLimit Paged="TRUE">30</RowLimit>
        <ViewFields>
          <FieldRef Name="LinkTitleNoMenu">
          </FieldRef>
        </ViewFields>
        <Query>
          <OrderBy>
            <FieldRef Name="Modified" Ascending="FALSE">
            </FieldRef>
          </OrderBy>
        </Query>
        <ParameterBindings>
          <ParameterBinding Name="AddNewAnnouncement" Location="Resource(wss,addnewitem)" />
          <ParameterBinding Name="NoAnnouncements" Location="Resource(wss,noXinviewofY_LIST)" />
          <ParameterBinding Name="NoAnnouncementsHowTo" Location="Resource(wss,noXinviewofY_ONET_HOME)" />
        </ParameterBindings>
      </View>
      <View BaseViewID="1" Type="HTML" WebPartZoneID="Main" DisplayName="$Resources:core,objectiv_schema_mwsidcamlidC24;" DefaultView="TRUE" MobileView="TRUE" MobileDefaultView="TRUE" SetupPath="pages\viewpage.aspx" ImageUrl="/_layouts/images/generic.png" Url="AllItems.aspx">
        <Toolbar Type="Standard" />
        <XslLink Default="TRUE">main.xsl</XslLink>
        <RowLimit Paged="TRUE">30</RowLimit>
        <ViewFields>
          <FieldRef Name="Attachments">
          </FieldRef>
          <FieldRef Name="LinkTitle">
          </FieldRef>
          <FieldRef ID="{40070CB4-6ED0-4024-9269-70DAC8932C42}" Name="SecurityEscortCatalog2BusinessDescriptionTitle" />
          <FieldRef ID="{4E19EC40-3A94-453E-ABEA-4DCBE1BF8ECD}" Name="EscortDestination" />
          <FieldRef ID="{40088770-43E3-441B-9973-D3B093DC131C}" Name="RemarkMM" />
          <FieldRef ID="{B5D7D15B-E7BA-4768-B746-AC71D70EF53F}" Name="FreightPayerTitle" />
          <FieldRef ID="{7BE8C54A-009F-436D-80C3-2E13A3F4A514}" Name="MaterialMaster" />
          <FieldRef ID="{C7CA4AA6-8399-4714-A4A4-42145FABA936}" Name="PartnerTitle" />
          <FieldRef ID="{D73A3F7D-6892-4A46-90EE-39BEB668944A}" Name="SecurityCost" />
          <FieldRef ID="{E1C985AA-F1A4-4275-87D3-EE0DF7B44223}" Name="CurrencyTitle" />
          <FieldRef ID="{DBCFB052-FB4A-46C1-B72E-BB92F9825142}" Name="SecurityEscrotPO" />
        </ViewFields>
        <Query>
          <OrderBy>
            <FieldRef Name="ID">
            </FieldRef>
          </OrderBy>
        </Query>
        <ParameterBindings>
          <ParameterBinding Name="NoAnnouncements" Location="Resource(wss,noXinviewofY_LIST)" />
          <ParameterBinding Name="NoAnnouncementsHowTo" Location="Resource(wss,noXinviewofY_DEFAULT)" />
        </ParameterBindings>
      </View>
      <View BaseViewID="2" Type="HTML" WebPartZoneID="Main" DisplayName="OutboundCoordinator" DefaultView="FALSE" MobileView="TRUE" MobileDefaultView="FALSE" SetupPath="pages\viewpage.aspx" ImageUrl="/_layouts/images/generic.png" Url="OutboundCoordinator.aspx">
        <Toolbar Type="None" />
        <XslLink Default="TRUE">main.xsl</XslLink>
        <RowLimit Paged="TRUE">10</RowLimit>
        <ViewFields>
          <FieldRef Name="LinkTitle">
          </FieldRef>
          <FieldRef ID="{C7CA4AA6-8399-4714-A4A4-42145FABA936}" Name="PartnerTitle" />
          <FieldRef ID="{40070CB4-6ED0-4024-9269-70DAC8932C42}" Name="SecurityEscortCatalog2BusinessDescriptionTitle" />
          <FieldRef ID="{4E19EC40-3A94-453E-ABEA-4DCBE1BF8ECD}" Name="EscortDestination" />
          <FieldRef ID="{DBCFB052-FB4A-46C1-B72E-BB92F9825142}" Name="SecurityEscrotPO" />
        </ViewFields>
        <Query>
          <OrderBy>
            <FieldRef Name="ID">
            </FieldRef>
          </OrderBy>
        </Query>
        <ParameterBindings>
          <ParameterBinding Name="NoAnnouncements" Location="Resource(wss,noXinviewofY_LIST)" />
          <ParameterBinding Name="NoAnnouncementsHowTo" Location="Resource(wss,noXinviewofY_DEFAULT)" />
        </ParameterBindings>
      </View>
      <View BaseViewID="3" Type="HTML" WebPartZoneID="Main" DisplayName="SecurityEscort" DefaultView="FALSE" MobileView="TRUE" MobileDefaultView="FALSE" SetupPath="pages\viewpage.aspx" ImageUrl="/_layouts/images/generic.png" Url="SecurityEscort.aspx">
        <Toolbar Type="None" />
        <XslLink Default="TRUE">main.xsl</XslLink>
        <RowLimit Paged="TRUE">1</RowLimit>
        <ViewFields>
          <FieldRef Name="LinkTitle">
          </FieldRef>
          <FieldRef ID="{40070CB4-6ED0-4024-9269-70DAC8932C42}" Name="SecurityEscortCatalog2BusinessDescriptionTitle" />
          <FieldRef ID="{4E19EC40-3A94-453E-ABEA-4DCBE1BF8ECD}" Name="EscortDestination" />
          <FieldRef ID="{DBCFB052-FB4A-46C1-B72E-BB92F9825142}" Name="SecurityEscrotPO" />
        </ViewFields>
        <Query>
          <OrderBy>
            <FieldRef Name="ID">
            </FieldRef>
          </OrderBy>
        </Query>
        <ParameterBindings>
          <ParameterBinding Name="NoAnnouncements" Location="Resource(wss,noXinviewofY_LIST)" />
          <ParameterBinding Name="NoAnnouncementsHowTo" Location="Resource(wss,noXinviewofY_DEFAULT)" />
        </ParameterBindings>
      </View>
    </Views>
    <Forms>
      <Form Type="DisplayForm" Url="DispForm.aspx" SetupPath="pages\form.aspx" WebPartZoneID="Main" />
      <Form Type="EditForm" Url="EditForm.aspx" SetupPath="pages\form.aspx" WebPartZoneID="Main" />
      <Form Type="NewForm" Url="NewForm.aspx" SetupPath="pages\form.aspx" WebPartZoneID="Main" />
    </Forms>
  </MetaData>
</List>