<?xml version="1.0" encoding="utf-8"?>
<Elements xmlns="http://schemas.microsoft.com/sharepoint/">
  <ContentType ID="0x01002bd66f0631854603a0815888852526d0"
               Name="FreightPayer"
               Group="CAS Smart Factory Shepherd"
               Description="$Resources:CASSmartFactoryShepherd,CAS_FreightPayerCT"
               Overwrite="TRUE"
               Inherits="FALSE">
    <Folder TargetName="_cts/FreightPayer" />
    <FieldRefs>
      <FieldRef ID="{fa564e0f-0c70-4ab9-b863-0177e6ddd247}" Name="Title" DisplayName="$Resources:CASSmartFactoryShepherd,CAS_FreightPayerNo" />
      <FieldRef ID="{654389E7-36DA-4528-AEC7-E6BB99634022}" Name="PayerName" />
      <FieldRef ID="{E0BCC826-1F93-4156-8FC1-7F4506234DFA}" Name="CompanyAddress" />
      <FieldRef ID="{9a631556-3dac-49db-8d2f-fb033b0fdc24}" Name="WorkZip" />
      <FieldRef ID="{6ca7bd7f-b490-402e-af1b-2813cf087b1e}" Name="WorkCity" />
      <FieldRef ID="{3f3a5c85-9d5a-4663-b925-8b68a678ea3a}" Name="WorkCountry" />
      <FieldRef ID="{DC0E5632-A487-412B-AA3E-4CC025116C28}" Name="NIP" />
      <FieldRef ID="{6D1FB660-86D4-48A2-92AE-91C4773A29EF}" Name="SendInvoiceToMultiline" />
    </FieldRefs>
    <XmlDocuments>
      <XmlDocument NamespaceURI="http://schemas.microsoft.com/sharepoint/v3/contenttype/forms">
        <FormTemplates xmlns="http://schemas.microsoft.com/sharepoint/v3/contenttype/forms">
          <Display>ListForm</Display>
          <Edit>ListForm</Edit>
          <New>ListForm</New>
        </FormTemplates>
      </XmlDocument>
    </XmlDocuments>
  </ContentType>
</Elements>
