<?xml version="1.0" encoding="utf-8"?>
<RequestContent xmlns="http://cas.eu/schemas/SmartFactory/CW/Interoperability/DocumentsFactory/RequestContent.xsd">
  <DocumentName>DocumentName1</DocumentName>
  <DocumentNo>1</DocumentNo>
  <DocumentDate>1900-01-01</DocumentDate>
  <IntroducingSADDocumentNo>IntroducingSADDocumentNo1</IntroducingSADDocumentNo>
  <IntroducingSADDocumentDate>1900-01-01</IntroducingSADDocumentDate>
  <WithdrawalSADDcoumentNo>WithdrawalSADDcoumentNo1</WithdrawalSADDcoumentNo>
  <WithdrawalSADDocumentDate>1900-01-01</WithdrawalSADDocumentDate>
  <ConsentNo>ConsentNo1</ConsentNo>
  <ConsentDate>1900-01-01</ConsentDate>
  <TobaccoName>TobaccoName1</TobaccoName>
  <Grade>Grade1</Grade>
  <SKU>SKU1</SKU>
  <Batch>Batch1</Batch>
  <CNTarrifCode>CNTarrifCode1</CNTarrifCode>
  <Quantity>1</Quantity>
  <NetMass>1</NetMass>
  <GrossMass>1</GrossMass>
  <PackageUnits>1</PackageUnits>
  <Value>1</Value>
  <Currency>Currency1</Currency>
  <UnitPrice>1</UnitPrice>
  <PzNo>PzNo1</PzNo>
  <InvoiceNo>InvoiceNo1</InvoiceNo>
  <DisposalsColection>
    <DisposalsArray>
      <No>1</No>
      <SADDocumentNo>SADDocumentNo1</SADDocumentNo>
      <SADDate>1900-01-01</SADDate>
      <SettledNetMass>1</SettledNetMass>
      <SettledGrossMass>1</SettledGrossMass>
      <TobaccoValue>1</TobaccoValue>
      <Currency>Currency1</Currency>
      <PackageToClear>1</PackageToClear>
      <WZ>WZ1</WZ>
      <RemainingQuantity>1</RemainingQuantity>
      <RemainingPackage>1</RemainingPackage>
      <CNTarrifCode>CNTarrifCode1</CNTarrifCode>
    </DisposalsArray>
    <DisposalsArray>
      <No>-1.7976931348623157E+308</No>
      <SADDocumentNo>SADDocumentNo2</SADDocumentNo>
      <SADDate>0001-01-01</SADDate>
      <SettledNetMass>-1.7976931348623157E+308</SettledNetMass>
      <SettledGrossMass>-1.7976931348623157E+308</SettledGrossMass>
      <TobaccoValue>-1.7976931348623157E+308</TobaccoValue>
      <Currency>Currency2</Currency>
      <PackageToClear>-1.7976931348623157E+308</PackageToClear>
      <WZ>WZ2</WZ>
      <RemainingQuantity>-1.7976931348623157E+308</RemainingQuantity>
      <RemainingPackage>-1.7976931348623157E+308</RemainingPackage>
      <CNTarrifCode>CNTarrifCode2</CNTarrifCode>
    </DisposalsArray>
    <DisposalsArray>
      <No>1.7976931348623157E+308</No>
      <SADDocumentNo>SADDocumentNo3</SADDocumentNo>
      <SADDate>9999-12-31</SADDate>
      <SettledNetMass>1.7976931348623157E+308</SettledNetMass>
      <SettledGrossMass>1.7976931348623157E+308</SettledGrossMass>
      <TobaccoValue>1.7976931348623157E+308</TobaccoValue>
      <Currency>Currency3</Currency>
      <PackageToClear>1.7976931348623157E+308</PackageToClear>
      <WZ>WZ3</WZ>
      <RemainingQuantity>1.7976931348623157E+308</RemainingQuantity>
      <RemainingPackage>1.7976931348623157E+308</RemainingPackage>
      <CNTarrifCode>CNTarrifCode3</CNTarrifCode>
    </DisposalsArray>
  </DisposalsColection>
</RequestContent>